tds2/__init__.py
tds2/tds2.py
tds2-0.2.2.dist-info/licenses/LICENSE
tds2-0.2.2.dist-info/METADATA
tds2-0.2.2.dist-info/WHEEL
tds2-0.2.2.dist-info/top_level.txt
tds2-0.2.2.dist-info/RECORD
