Metadata-Version: 2.4
Name: tds2
Version: 0.2.2
Summary: lib for file management with telegram api
Home-page: https://github.com/ZatON318/TDS2
Author: ZatOFF
Author-email: zaton318@gmail.com
Classifier: Programming Language :: Python :: 3
Classifier: License :: OSI Approved :: MIT License
Classifier: Operating System :: OS Independent
Requires-Python: >=3.6
License-File: LICENSE
Requires-Dist: telethon
Requires-Dist: tqdm
Requires-Dist: python-dotenv
Dynamic: author
Dynamic: author-email
Dynamic: classifier
Dynamic: description
Dynamic: description-content-type
Dynamic: home-page
Dynamic: license-file
Dynamic: requires-dist
Dynamic: requires-python
Dynamic: summary
